manim_livestream/__init__.py
manim_livestream/__main__.py
manim_livestream/cli.py
manim_livestream/config/__init__.py
manim_livestream/config/default.cfg
manim_livestream/config/logger_utils.py
manim_livestream/stream_file_writer.py
manim_livestream/stream_renderer.py
manim_livestream/stream_starter.py
manim_livestream/streaming_scene.py
manim_livestream/utils.py
manim_livestream-0.0.3.dist-info/entry_points.txt
manim_livestream-0.0.3.dist-info/WHEEL
manim_livestream-0.0.3.dist-info/METADATA
manim_livestream-0.0.3.dist-info/RECORD
