Metadata-Version: 2.1
Name: manim-livestream
Version: 0.0.3
Summary: Package that implements livestreaming configurations for Manim.
Home-page: https://github.com/NeoPlato/manim-livestream
License: MIT
Author: NeoPlato
Requires-Python: >=3.7,<4.0
Classifier: Development Status :: 4 - Beta
Classifier: License :: OSI Approved :: MIT License
Classifier: Natural Language :: English
Classifier: Programming Language :: Python :: 3
Classifier: Programming Language :: Python :: 3.6
Classifier: Programming Language :: Python :: 3.7
Classifier: Programming Language :: Python :: 3.8
Classifier: Programming Language :: Python :: 3.9
Classifier: Topic :: Multimedia :: Graphics
Classifier: Topic :: Multimedia :: Video
Classifier: Topic :: Scientific/Engineering
Requires-Dist: ipython (>=7.25.0,<8.0.0); python_version >= "3.7" and python_version < "4.0.0"
Requires-Dist: manim (>=0.10)
Requires-Dist: pyreadline (>=2.1,<3.0); sys_platform == "win32"
Project-URL: Documentation, https://docs.manim.community/en/latest/installation/plugins.html
Project-URL: Repository, https://github.com/NeoPlato/manim-livestream
